benchpots/__init__.py
benchpots/version.py
benchpots/datasets/__init__.py
benchpots/datasets/beijing_multisite_air_quality.py
benchpots/datasets/electricity_load_diagrams.py
benchpots/datasets/electricity_transformer_temperature.py
benchpots/datasets/italy_air_quality.py
benchpots/datasets/pems_traffic.py
benchpots/datasets/physionet_2012.py
benchpots/datasets/physionet_2019.py
benchpots/datasets/random_walk.py
benchpots/datasets/solar_alabama.py
benchpots/datasets/ucr_uea_datasets.py
benchpots/utils/__init__.py
benchpots/utils/logging.py
benchpots/utils/missingness.py
benchpots/utils/sliding.py
benchpots-0.4.dist-info/licenses/LICENSE
benchpots-0.4.dist-info/METADATA
benchpots-0.4.dist-info/WHEEL
benchpots-0.4.dist-info/top_level.txt
benchpots-0.4.dist-info/RECORD
