Metadata-Version: 2.4
Name: benchpots
Version: 0.4
Summary: A Python Toolbox for Benchmarking Machine Learning on Partially-Observed Time Series
Author-email: Wenjie Du <wenjay.du@gmail.com>
License: Copyright (c) 2024-present, Wenjie Du
Project-URL: Source, https://github.com/WenjieDu/BenchPOTS
Project-URL: Homepage, https://pypots.com
Project-URL: Documentation, https://docs.pypots.com
Project-URL: Bug Tracker, https://github.com/WenjieDu/BenchPOTS/issues
Project-URL: Download, https://github.com/WenjieDu/BenchPOTS/archive/main.zip
Keywords: data mining,benchmark,neural networks,machine learning,deep learning,artificial intelligence,time-series analysis,time series,imputation,classification,clustering,forecasting,partially observed,irregular sampled,partially-observed time series,incomplete time series,missing data,missing values
Classifier: Development Status :: 5 - Production/Stable
Classifier: Intended Audience :: Developers
Classifier: Intended Audience :: Education
Classifier: Intended Audience :: Science/Research
Classifier: License :: OSI Approved :: BSD License
Classifier: Operating System :: OS Independent
Classifier: Programming Language :: Python :: 3
Classifier: Topic :: Scientific/Engineering :: Artificial Intelligence
Classifier: Topic :: Software Development :: Libraries :: Application Frameworks
Requires-Python: >=3.8
License-File: LICENSE
Requires-Dist: h5py
Requires-Dist: numpy
Requires-Dist: pandas
Requires-Dist: scikit-learn
Requires-Dist: torch>=1.10
Requires-Dist: tsdb>=0.7.1
Requires-Dist: pygrinder>=0.7
Dynamic: license-file
